attribution/__init__.py
attribution/__main__.py
attribution/__version__.py
attribution/generate.py
attribution/helpers.py
attribution/main.py
attribution/project.py
attribution/py.typed
attribution/tag.py
attribution/types.py
attribution/tests/__init__.py
attribution/tests/__main__.py
attribution/tests/generate.py
attribution/tests/helpers.py
attribution/tests/project.py
attribution/tests/tag.py
attribution/tests/fake_crate/Cargo.lock
attribution/tests/fake_crate/Cargo.toml
attribution/tests/fake_crate/src/lib.rs
attribution-1.8.0.dist-info/entry_points.txt
attribution-1.8.0.dist-info/LICENSE
attribution-1.8.0.dist-info/WHEEL
attribution-1.8.0.dist-info/METADATA
attribution-1.8.0.dist-info/RECORD
