Metadata-Version: 2.1
Name: attribution
Version: 1.8.0
Summary: Generate changelogs based on tag messages and shortlogs
Author-email: Amethyst Reese <amethyst@n7.gg>
Requires-Python: >=3.8
Classifier: Development Status :: 4 - Beta
Classifier: Intended Audience :: Developers
Classifier: License :: OSI Approved :: MIT License
Classifier: Topic :: Software Development :: Version Control
Classifier: Topic :: Software Development :: Documentation
Classifier: Topic :: Software Development :: Version Control :: Git
Classifier: Topic :: Utilities
Classifier: Typing :: Typed
Requires-Dist: click >= 8.0
Requires-Dist: jinja2 >= 2.7
Requires-Dist: packaging >= 16.2
Requires-Dist: tomlkit >= 0.7.0
Requires-Dist: black==24.4.2 ; extra == "dev"
Requires-Dist: coverage==7.5.3 ; extra == "dev"
Requires-Dist: flake8==7.1.0 ; extra == "dev"
Requires-Dist: flake8-bugbear==24.4.26 ; extra == "dev"
Requires-Dist: flit==3.9.0 ; extra == "dev"
Requires-Dist: mypy==1.10.0 ; extra == "dev"
Requires-Dist: pessimist==0.9.3 ; extra == "dev"
Requires-Dist: rich==13.7.1 ; extra == "dev"
Requires-Dist: ufmt==2.6.0 ; extra == "dev"
Requires-Dist: usort==1.0.8.post1 ; extra == "dev"
Requires-Dist: wheel==0.43.0 ; extra == "dev"
Requires-Dist: sphinx==7.3.7 ; extra == "docs"
Requires-Dist: sphinx-mdinclude==0.6.1 ; extra == "docs"
Project-URL: Changelog, https://attribution.omnilib.dev/en/latest/changelog.html
Project-URL: Documentation, https://attribution.omnilib.dev
Project-URL: Github, https://github.com/omnilib/attribution
Provides-Extra: dev
Provides-Extra: docs
